switches/__init__.py
switches/switch.py
tests/__init__.py
tests/funcs.py
tests/test.py
switches.py-0.1.0.dist-info/LICENSE.txt
switches.py-0.1.0.dist-info/METADATA
switches.py-0.1.0.dist-info/WHEEL
switches.py-0.1.0.dist-info/top_level.txt
switches.py-0.1.0.dist-info/RECORD
