Metadata-Version: 2.1
Name: switches.py
Version: 0.1.0
Summary: Use C-like switch construct (and more!) in Python
Home-page: https://github.com/ziord/switches
Author: Jeremiah Ikosin <@ziord>
License: MIT
Project-URL: Documentation, https://github.com/ziord/switches/blob/master/README.md
Project-URL: Source Code, https://github.com/ziord/switches
Keywords: python switch C
Platform: UNKNOWN
Classifier: Programming Language :: Python :: 3
Classifier: Operating System :: OS Independent
Requires-Python: >=3.6
